haxagongrades/__init__.py
haxagongrades/cli.py
haxagongrades/main.py
haxagongrades/utility.py
haxagongrades-1.0.0a1.dist-info/LICENSE
haxagongrades-1.0.0a1.dist-info/METADATA
haxagongrades-1.0.0a1.dist-info/WHEEL
haxagongrades-1.0.0a1.dist-info/entry_points.txt
haxagongrades-1.0.0a1.dist-info/RECORD
