Metadata-Version: 2.1
Name: haxagongrades
Version: 1.0.0a1
Summary: Haxagon Grades CLI is a command-line tool designed to manage and generate reports for Haxagon classes. The tool allows you to fetch and export class reports in different formats.
Author: Daniel Kopecký
Author-email: kopecky.d@gmail.com
Requires-Python: >=3.11,<4.0
Classifier: Programming Language :: Python :: 3
Classifier: Programming Language :: Python :: 3.11
Classifier: Programming Language :: Python :: 3.12
Requires-Dist: click (>=8.1.7,<9.0.0)
Requires-Dist: loguru (>=0.7.2,<0.8.0)
Requires-Dist: pandas (>=2.2.2,<3.0.0)
Requires-Dist: selenium (>=4.21.0,<5.0.0)
Requires-Dist: tqdm (>=4.66.4,<5.0.0)
Requires-Dist: webdriver-manager (>=4.0.1,<5.0.0)
